QTileLayout/__init__.py
QTileLayout/tile.py
QTileLayout/tileLayout.py
pyqt5_tile_layout-0.1.7.dist-info/LICENSE
pyqt5_tile_layout-0.1.7.dist-info/METADATA
pyqt5_tile_layout-0.1.7.dist-info/WHEEL
pyqt5_tile_layout-0.1.7.dist-info/top_level.txt
pyqt5_tile_layout-0.1.7.dist-info/RECORD
